{
  "mode": "letters",
  "panelCollapsed": false,
  "flowOverlayEnable": true,
  "flowOverlayOpacity": "0.96",
  "flowEffect": "shockwaves",
  "flowEffectIntensity": "0",
  "flowShape": "diamond",
  "intensity": "1.75",
  "word": "Masters of Disasters",
  "textColor": "#ffffff",
  "textFont": "chicle",
  "textSize": "0.5",
  "textX": "0",
  "textY": "20",
  "bevelEnable": true,
  "bevelDepth": "4",
  "bevelHighlight": "0.7",
  "bevelShadow": "0.65",
  "glowEnabled": false,
  "outlineEnable": true,
  "outlineColor": "#2e073e",
  "outlineThickness": "3",
  "leftSignal": "blended:melodic",
  "leftGain": "1.65",
  "midSignal": "stems:drums.rms",
  "midGain": "3",
  "rightSignal": "blended:melodic",
  "rightGain": "1.35",
  "bandSpread": "0.41",
  "ghostSize": "1.25",
  "ghostColor": "#e392fe",
  "ghostDecay": "0.2",
  "ghostOpacity": "0.06",
  "glowOpacity": "0.06",
  "ghostEnable": true,
  "ghostFill": false,
  "borderWidth": "1.55",
  "borderGain": "1",
  "borderOpacity": "1.5",
  "borderTint": "#ff40ff",
  "borderSignal": "blended:melodic",
  "borderFreqDiv": "4",
  "globalTintColor": "#61177c",
  "globalTintOpacity": "0.62",
  "masterTintEnable": true,
  "videoShift": "115",
  "videoShiftSweepEnable": true,
  "videoShiftSweepDiv": "64",
  "masterTintBaseGhost": "#e392fe",
  "masterTintBaseBorder": "#ff40ff",
  "masterTintBaseGlobal": "#61177c"
}